JuniperZhongwenWendangFix1/README.md
JuniperZhongwenWendangFix1/__init__.py
JuniperZhongwenWendangFix1/__main__.py
JuniperZhongwenWendangFix1/file.epub
JuniperZhongwenWendangFix1/index.html
JuniperZhongwenWendangFix1/css/__init__.py
JuniperZhongwenWendangFix1/css/annotations.css
JuniperZhongwenWendangFix1/css/main.css
JuniperZhongwenWendangFix1/css/normalize.css
JuniperZhongwenWendangFix1/css/popup.css
JuniperZhongwenWendangFix1/font/__init__.py
JuniperZhongwenWendangFix1/font/fontello.eot
JuniperZhongwenWendangFix1/font/fontello.svg
JuniperZhongwenWendangFix1/font/fontello.ttf
JuniperZhongwenWendangFix1/font/fontello.woff
JuniperZhongwenWendangFix1/img/__init__.py
JuniperZhongwenWendangFix1/img/annotator-glyph-sprite.png
JuniperZhongwenWendangFix1/img/annotator-icon-sprite.png
JuniperZhongwenWendangFix1/img/apple-touch-icon.png
JuniperZhongwenWendangFix1/img/cancelfullscreen.png
JuniperZhongwenWendangFix1/img/close.png
JuniperZhongwenWendangFix1/img/fullscreen.png
JuniperZhongwenWendangFix1/img/loader.gif
JuniperZhongwenWendangFix1/img/menu-icon.png
JuniperZhongwenWendangFix1/img/save.png
JuniperZhongwenWendangFix1/img/saved.png
JuniperZhongwenWendangFix1/img/settings-s.png
JuniperZhongwenWendangFix1/img/settings.png
JuniperZhongwenWendangFix1/img/star.png
JuniperZhongwenWendangFix1/js/__init__.py
JuniperZhongwenWendangFix1/js/epub.js
JuniperZhongwenWendangFix1/js/epub.min.js
JuniperZhongwenWendangFix1/js/epub.min.map
JuniperZhongwenWendangFix1/js/hooks.min.js
JuniperZhongwenWendangFix1/js/hooks.min.map
JuniperZhongwenWendangFix1/js/reader.js
JuniperZhongwenWendangFix1/js/reader.js.map
JuniperZhongwenWendangFix1/js/reader.min.js
JuniperZhongwenWendangFix1/js/reader.min.map
JuniperZhongwenWendangFix1/js/hooks/__init__.py
JuniperZhongwenWendangFix1/js/hooks/extensions/__init__.py
JuniperZhongwenWendangFix1/js/hooks/extensions/highlight.js
JuniperZhongwenWendangFix1/js/libs/__init__.py
JuniperZhongwenWendangFix1/js/libs/jquery.min.js
juniper_zhongwen_wendang_fix1-2025.3.25.1.dist-info/METADATA
juniper_zhongwen_wendang_fix1-2025.3.25.1.dist-info/WHEEL
juniper_zhongwen_wendang_fix1-2025.3.25.1.dist-info/entry_points.txt
juniper_zhongwen_wendang_fix1-2025.3.25.1.dist-info/top_level.txt
juniper_zhongwen_wendang_fix1-2025.3.25.1.dist-info/RECORD
